generic_oauth_nic/__init__.py
generic_oauth_nic/oauth.py
generic_oauth_nic-0.1.0.dist-info/METADATA
generic_oauth_nic-0.1.0.dist-info/WHEEL
generic_oauth_nic-0.1.0.dist-info/top_level.txt
generic_oauth_nic-0.1.0.dist-info/RECORD
