Metadata-Version: 2.1
Name: generic_oauth_nic
Version: 0.1.0
Summary: A generic OAuth authentication library for multiple providers
Author: Binay Raj Parajuli
Author-email: binayaparajuli17@egmail.com
Classifier: Programming Language :: Python :: 3
Classifier: License :: OSI Approved :: MIT License
Classifier: Operating System :: OS Independent
Requires-Dist: requests
Requires-Dist: python-dotenv
